youcan/__init__.py
youcan/base.py
youcan/menu.py
youcan/page.py
youcan/product.py
youcan-1.0.0.dist-info/METADATA
youcan-1.0.0.dist-info/WHEEL
youcan-1.0.0.dist-info/top_level.txt
youcan-1.0.0.dist-info/RECORD
