Metadata-Version: 2.1
Name: youcan
Version: 1.0.0
Summary: YOUcan Python SDK
Home-page: UNKNOWN
Author: Adam Louly
Author-email: adamlouly3@gmail.com
License: UNKNOWN
Platform: UNKNOWN
Requires-Dist: requests
